methodidentityvalidate/__init__.py
methodidentityvalidate/core/__init__.py
methodidentityvalidate/core/datetime_utils.py
methodidentityvalidate/core/pydantic_utilities.py
methodidentityvalidate/core/serialization.py
methodidentityvalidate/py.typed
methodidentityvalidate/resources/__init__.py
methodidentityvalidate/resources/common/__init__.py
methodidentityvalidate/resources/common/http_method.py
methodidentityvalidate/resources/portal/__init__.py
methodidentityvalidate/resources/portal/attempt_info_union.py
methodidentityvalidate/resources/portal/general_attempt_info.py
methodidentityvalidate/resources/portal/general_request_info.py
methodidentityvalidate/resources/portal/general_response_info.py
methodidentityvalidate/resources/portal/module_name.py
methodidentityvalidate/resources/portal/portal_config.py
methodidentityvalidate/resources/portal/portal_report.py
methodidentityvalidate/resources/portal/portal_type.py
methodidentityvalidate/resources/portal/response_union.py
methodidentityvalidate/resources/portal/trigger.py
methodidentityvalidate-0.0.1.dist-info/METADATA
methodidentityvalidate-0.0.1.dist-info/WHEEL
methodidentityvalidate-0.0.1.dist-info/RECORD
